my_sample_package_fjornelas/__init__.py
my_sample_package_fjornelas/main.py
my_sample_package_fjornelas-0.0.1.dist-info/LICENSE
my_sample_package_fjornelas-0.0.1.dist-info/METADATA
my_sample_package_fjornelas-0.0.1.dist-info/WHEEL
my_sample_package_fjornelas-0.0.1.dist-info/top_level.txt
my_sample_package_fjornelas-0.0.1.dist-info/RECORD
