Metadata-Version: 2.1
Name: my-sample-package-fjornelas
Version: 0.0.1
Summary: simple test package
Home-page: UNKNOWN
Author: Javier Ornelas
Author-email: jornela1@g.ucla.edu
License: UNKNOWN
Platform: UNKNOWN
License-File: LICENSE
